{
  "irdi": "0112/2///61987#ABD684",
  "code": "ABD684",
  "version": "1",
  "revision": "4",
  "preferred_name": "overshoot",
  "preferred_name_ml": {
    "en": "overshoot",
    "de": "Überschwingen"
  },
  "definition": "for a step response, the maximum transient deviation from the final steady-state value of the output variable, expressed as a percentage of the difference between the final and the initial steady-state values",
  "definition_ml": {
    "en": "for a step response, the maximum transient deviation from the final steady-state value of the output variable, expressed as a percentage of the difference between the final and the initial steady-state values",
    "de": "für eine Sprungantwort die maximale Regelabweichung des stationären Endwertes der Ausgangsgröße, ausgedrückt als Prozentsatz der Differenz zwischen den End- und den Anfangswerten des stationären Betriebszustandes"
  },
  "source_document": "IEC 60534-9",
  "synonyms": [],
  "status_level": "Standard",
  "change_request_id": "C00004",
  "raw_properties": {
    "MDC_P001_6": "0112/2///61987#ABD684",
    "MDC_P002_1": "1",
    "MDC_P002_2": "4",
    "MDC_P004.en": "overshoot",
    "MDC_P006.en": "for a step response, the maximum transient deviation from the final steady-state value of the output variable, expressed as a percentage of the difference between the final and the initial steady-state values",
    "MDC_P023": "%",
    "MDC_P022": "REAL_MEASURE_TYPE",
    "MDC_P006_1": "IEC 60534-9",
    "MDC_P020": "NON_DEPENDENT_P_DET",
    "MDC_P021": "0112/2///61987#ABA000",
    "MDC_P041": "0112/2///62720#UAA000",
    "C0104": "0112/2///61987#ABT533",
    "C016": "Standard",
    "MDC_P003_0": "2018-03-28",
    "MDC_P003_1": "2013-09-02",
    "MDC_P003_2": "2013-10-16",
    "MDC_P003_3": "2016-09-30",
    "MDC_P004.de": "Überschwingen",
    "MDC_P006.de": "für eine Sprungantwort die maximale Regelabweichung des stationären Endwertes der Ausgangsgröße, ausgedrückt als Prozentsatz der Differenz zwischen den End- und den Anfangswerten des stationären Betriebszustandes",
    "C019.de": "Mr. W. Hartmann",
    "C017.de": "0",
    "C018.de": "2013-10-16",
    "C002": "C00004"
  },
  "version_history": [
    {
      "version": "001",
      "revision": "04",
      "status": "standard",
      "timestamp": "2018-03-28 07:26:57",
      "user": "BATCH 00000762",
      "unid": "61BE9AF8F8605225C125825E001DEEEA",
      "is_current": true
    },
    {
      "version": "001",
      "revision": "03",
      "status": "superseded",
      "timestamp": "2016-05-02 13:42:58",
      "user": "BATCH 00000717",
      "unid": "155061c3d2c890d3c1257fa700405c14",
      "is_current": false
    },
    {
      "version": "001",
      "revision": "02",
      "status": "superseded",
      "timestamp": "2014-06-18 13:41:50",
      "user": "BATCH 00000702",
      "unid": "8f350bc4afa1278ac1257cfb00404170",
      "is_current": false
    },
    {
      "version": "001",
      "revision": "01",
      "status": "superseded",
      "timestamp": "2014-04-08 17:25:49",
      "user": "BATCH 00000699",
      "unid": "31ba9a7beb37cd3bc1257cb40054c32d",
      "is_current": false
    }
  ],
  "dates": {
    "original_definition": "2013-09-02",
    "current_version": "2013-10-16",
    "current_revision": "2016-09-30"
  },
  "definition_class_irdi": "0112/2///61987#ABA000",
  "unit_irdi": "0112/2///62720#UAA000",
  "alternative_unit_irdis": [],
  "parsed_data_type": "REAL_MEASURE_TYPE",
  "data_element_type": "NON_DEPENDENT_P_DET",
  "property_data_element_type": "NON_DEPENDENT_P_DET",
  "type": "property",
  "data_type": "REAL_MEASURE_TYPE",
  "is_current": true,
  "version_meta": {
    "version": "001",
    "revision": "04",
    "status": "standard",
    "timestamp": "2018-03-28 07:26:57",
    "user": "BATCH 00000762",
    "change_request_id": null,
    "unid": "61BE9AF8F8605225C125825E001DEEEA"
  }
}