{
  "irdi": "0112/2///62683#ACC601",
  "code": "ACC601",
  "version": "2",
  "revision": "1",
  "preferred_name": "Transfer switching equipment",
  "preferred_name_ml": {
    "en": "Transfer switching equipment",
    "fr": "Equipement de transfert de source",
    "de": "Netzumschalter",
    "zh": "转换开关电器"
  },
  "definition": "equipment containing one or more switching devices and associated operating mechanism for disconnecting load circuits from one supply and connecting to another supply",
  "definition_ml": {
    "en": "equipment containing one or more switching devices and associated operating mechanism for disconnecting load circuits from one supply and connecting to another supply",
    "fr": "matériel qui comporte un ou plusieurs appareils de connexion et un mécanisme de manœuvre associé, destiné à la déconnexion de circuits de charge d'une source d'alimentation et à leur connexion à une autre source d'alimentation",
    "de": "Einrichtung,die ein oder mehrere Schaltgeräte und den zugehörigen Betätigungsmechanismus fürdas Trennen von Lastkreisen von einem Versorgungsnetz und das Verbinden mit einem anderen Versorgungsnetz enthält",
    "zh": "包括一个或多个用于将负载电路从一个电源断开，连接到另一个电源的开关装置的设备。"
  },
  "source_document": "IEC 60947-6-1:2021, 3.3.1",
  "synonyms": [
    {
      "lang": "Manual transfer switch",
      "name": "Remote transfer switch"
    },
    {
      "lang": null,
      "name": "Automatic transfer switch"
    }
  ],
  "synonyms_ml": {
    "en": "Manual transfer switch, Remote transfer switch, Automatic transfer switch",
    "fr": "Inverseur de source",
    "de": "handbetätigter Netzumschalter, fernbetätigter Netzumschalter, automatischer Netzumschalter"
  },
  "status_level": "Standard",
  "publisher": "IEC",
  "published_in": "IEC 62683-1:2017",
  "responsible_committee": "IEC/TC 121",
  "change_request_id": "C00175",
  "raw_properties": {
    "MDC_P001_5": "0112/2///62683#ACC601",
    "MDC_P002_1": "2",
    "MDC_P002_2": "1",
    "MDC_P004.en": "Transfer switching equipment",
    "MDC_P007.en": "Manual transfer switch, Remote transfer switch, Automatic transfer switch",
    "MDC_P006.en": "equipment containing one or more switching devices and associated operating mechanism for disconnecting load circuits from one supply and connecting to another supply",
    "MDC_P006_1": "IEC 60947-6-1:2021, 3.3.1",
    "MDC_P011": "ITEM_CLASS",
    "MDC_P019": "true",
    "C016": "Standard",
    "C012": "IEC 62683-1:2017",
    "C011": "IEC",
    "MDC_P003_0": "2025-10-21",
    "MDC_P003_1": "2012-09-27",
    "MDC_P003_2": "2025-09-30",
    "MDC_P003_3": "2025-09-30",
    "MDC_P012": "IEC/TC 121",
    "MDC_P010": "0112/2///62683#ACC600",
    "MDC_P014": "{0112/2///62683#ACF001,0112/2///62683#ACF147,0112/2///62683#ACF150,0112/2///62683#ACF153,0112/2///62683#ACF155,0112/2///62683#ACF178,0112/2///62683#ACF181,0112/2///62683#ACF184,0112/2///62683#ACF701}",
    "MDC_P004.fr": "Equipement de transfert de source",
    "MDC_P007.fr": "Inverseur de source",
    "MDC_P006.fr": "matériel qui comporte un ou plusieurs appareils de connexion et un mécanisme de manœuvre associé, destiné à la déconnexion de circuits de charge d'une source d'alimentation et à leur connexion à une autre source d'alimentation",
    "MDC_P008.fr": "L’abréviation \"TSE\" est dérivée du terme anglais développé correspondant \"Transfer Switching Equipment\".",
    "C019.fr": "AFNOR",
    "C017.fr": "3",
    "C018.fr": "2025-03-14",
    "MDC_P004.de": "Netzumschalter",
    "MDC_P007.de": "handbetätigter Netzumschalter, fernbetätigter Netzumschalter, automatischer Netzumschalter",
    "MDC_P006.de": "Einrichtung,die ein oder mehrere Schaltgeräte und den zugehörigen Betätigungsmechanismus fürdas Trennen von Lastkreisen von einem Versorgungsnetz und das Verbinden mit einem anderen Versorgungsnetz enthält",
    "C019.de": "DKE, A Huhn",
    "C017.de": "3",
    "C018.de": "2025-10-10",
    "MDC_P004.zh": "转换开关电器",
    "MDC_P006.zh": "包括一个或多个用于将负载电路从一个电源断开，连接到另一个电源的开关装置的设备。",
    "C019.zh": "SAC, Li Hui",
    "C017.zh": "1",
    "C018.zh": "2017-09-26",
    "C002": "C00175"
  },
  "version_history": [
    {
      "version": "002",
      "revision": "01",
      "status": "standard",
      "timestamp": "2025-10-21 21:34:04",
      "user": "BATCH 00000844",
      "unid": "D03277DD6870C367C1258D2A006B7D71",
      "is_current": true
    },
    {
      "version": "001",
      "revision": "01",
      "status": "superseded",
      "timestamp": "2020-01-07 21:31:34",
      "user": "BATCH 00000739",
      "unid": "bfdc9fbeb06d7413c12584e80070c0fc",
      "is_current": false
    },
    {
      "version": "001",
      "revision": "01",
      "status": "superseded",
      "timestamp": "2016-09-16 14:33:45",
      "user": "BATCH 00000703",
      "unid": "62b2180117331e8dc125803000450228",
      "is_current": false
    }
  ],
  "dates": {
    "original_definition": "2012-09-27",
    "current_version": "2025-09-30",
    "current_revision": "2025-09-30"
  },
  "is_case_of": [],
  "applicable_properties": [
    "0112/2///62683#ACF001",
    "0112/2///62683#ACF147",
    "0112/2///62683#ACF150",
    "0112/2///62683#ACF153",
    "0112/2///62683#ACF155",
    "0112/2///62683#ACF178",
    "0112/2///62683#ACF181",
    "0112/2///62683#ACF184",
    "0112/2///62683#ACF701"
  ],
  "imported_properties": [],
  "sub_class_selection": [],
  "applicable_documents": [],
  "imported_documents": [],
  "class_type": "ITEM_CLASS",
  "superclass": "0112/2///62683#ACC600",
  "superclass_type_property": "0112/2///62683#ACC600",
  "type": "class",
  "is_current": true,
  "version_meta": {
    "version": "002",
    "revision": "01",
    "status": "standard",
    "timestamp": "2025-10-21 21:34:04",
    "user": "BATCH 00000844",
    "change_request_id": null,
    "unid": "D03277DD6870C367C1258D2A006B7D71"
  }
}