{
  "irdi": "0112/2///61360_4#AAE700",
  "code": "AAE700",
  "version": "1",
  "revision": "5",
  "preferred_name": "2nd-order beat",
  "preferred_name_ml": {
    "en": "2nd-order beat"
  },
  "short_name": "d_2",
  "short_name_ml": {
    "en": "d_2"
  },
  "definition": "value as specified by level (minTypmax) of the quotient of a wideband amplifier of: 1) the amplitude of the frequency component arising by the superposition of two input signals with specified amplitude and frequency (or channel) measured at a specified frequency (or channel), and 2) the amplitude of one of two original frequencies at specified supply voltage, temperature and temperature type",
  "definition_ml": {
    "en": "value as specified by level (minTypmax) of the quotient of a wideband amplifier of: 1) the amplitude of the frequency component arising by the superposition of two input signals with specified amplitude and frequency (or channel) measured at a specified frequency (or channel), and 2) the amplitude of one of two original frequencies at specified supply voltage, temperature and temperature type"
  },
  "synonyms": [],
  "remark": "Measuring method:| V_p} = V_o},   f_p} = f_1}   (channel p);| V_q} = V_o},   f_q} = f_2}   (channel q).| 2nd-order beat measured at (f_1} + f_2}).",
  "remark_ml": {
    "en": "Measuring method:| V_p} = V_o},   f_p} = f_1}   (channel p);| V_q} = V_o},   f_q} = f_2}   (channel q).| 2nd-order beat measured at (f_1} + f_2})."
  },
  "status_level": "Standard",
  "publisher": "IEC",
  "published_in": "IEC 61360-4",
  "responsible_committee": "SC3D",
  "raw_properties": {
    "MDC_P001_6": "0112/2///61360_4#AAE700",
    "MDC_P002_1": "1",
    "MDC_P002_2": "5",
    "MDC_P004.en": "2nd-order beat",
    "MDC_P005.en": "d_2",
    "MDC_P006.en": "value as specified by level (minTypmax) of the quotient of a wideband amplifier of: 1) the amplitude of the frequency component arising by the superposition of two input signals with specified amplitude and frequency (or channel) measured at a specified frequency (or channel), and 2) the amplitude of one of two original frequencies at specified supply voltage, temperature and temperature type",
    "MDC_P009.en": "Measuring method:| V_p} = V_o},   f_p} = f_1}   (channel p);| V_q} = V_o},   f_q} = f_2}   (channel q).| 2nd-order beat measured at (f_1} + f_2}).",
    "MDC_P025_1": "d_2}",
    "MDC_P023": "dB",
    "MDC_P022": "LEVEL(MIN,MAX,TYP) OF REAL_MEASURE_TYPE",
    "MDC_P024": "NR2 S..3.3",
    "MDC_P020": "DEPENDENT_P_DET",
    "MDC_P040": "E06",
    "MDC_P021": "0112/2///61360_4#AAA001",
    "MDC_P041": "0112/2///62720#UAA409",
    "C016": "Standard",
    "C012": "IEC 61360-4",
    "C011": "IEC",
    "MDC_P003_0": "2015-08-17",
    "MDC_P003_1": "1996-08-01",
    "MDC_P003_2": "2011-08-31",
    "MDC_P003_3": "2015-08-17",
    "MDC_P012": "SC3D",
    "MDC_P028": "{0112/2///61360_4#AAE102,0112/2///61360_4#AAE683,0112/2///61360_4#AAE685}"
  },
  "version_history": [
    {
      "version": "001",
      "revision": "05",
      "status": "standard",
      "timestamp": "2015-08-17 15:40:34",
      "user": "BATCH 00000917",
      "unid": "87100121F9F38816C1257EA4004B2051",
      "is_current": true
    },
    {
      "version": "001",
      "revision": "04",
      "status": "superseded",
      "timestamp": "2015-07-23 11:08:27",
      "user": "BATCH 00000907",
      "unid": "0958225e95f40b24c1257e8b003236a0",
      "is_current": false
    },
    {
      "version": "001",
      "revision": "03",
      "status": "superseded",
      "timestamp": "2015-07-22 14:21:33",
      "user": "BATCH 00000904",
      "unid": "10d537b8bfb65696c1257e8a0043e474",
      "is_current": false
    },
    {
      "version": "001",
      "revision": "02",
      "status": "superseded",
      "timestamp": "2012-05-30 15:03:33",
      "user": "BATCH 00000788",
      "unid": "640c64430889427dc1257a0e0047bcb6",
      "is_current": false
    },
    {
      "version": "001",
      "revision": "01",
      "status": "superseded",
      "timestamp": "2012-05-30 14:53:53",
      "user": "BATCH 00000787",
      "unid": "6dec27f5e0a77196c1257a0e0046da36",
      "is_current": false
    }
  ],
  "dates": {
    "original_definition": "1996-08-01",
    "current_version": "2011-08-31",
    "current_revision": "2015-08-17"
  },
  "symbol_in_text": "d_2}",
  "value_format": "NR2 S..3.3",
  "definition_class_irdi": "0112/2///61360_4#AAA001",
  "unit_irdi": "0112/2///62720#UAA409",
  "alternative_unit_irdis": [],
  "parsed_data_type": "LEVEL(MIN,MAX,TYP) OF REAL_MEASURE_TYPE",
  "data_element_type": "DEPENDENT_P_DET",
  "property_data_element_type": "DEPENDENT_P_DET",
  "parsed_value_format": "NR2 S..3.3",
  "condition_raw": "{0112/2///61360_4#AAE102,0112/2///61360_4#AAE683,0112/2///61360_4#AAE685}",
  "type": "property",
  "data_type": "LEVEL(MIN,MAX,TYP) OF REAL_MEASURE_TYPE",
  "is_current": true,
  "version_meta": {
    "version": "001",
    "revision": "05",
    "status": "standard",
    "timestamp": "2015-08-17 15:40:34",
    "user": "BATCH 00000917",
    "change_request_id": null,
    "unid": "87100121F9F38816C1257EA4004B2051"
  }
}