{
  "irdi": "0112/2///61360_4#AAF163",
  "code": "AAF163",
  "version": "1",
  "revision": "5",
  "preferred_name": "differential input resistance",
  "preferred_name_ml": {
    "en": "differential input resistance"
  },
  "short_name": "r_id",
  "short_name_ml": {
    "en": "r_id"
  },
  "definition": "minimum resistance between the inputs of a differential amplifier at reference conditions",
  "definition_ml": {
    "en": "minimum resistance between the inputs of a differential amplifier at reference conditions"
  },
  "source_document": "IEC 60748-3 (II.2.1.10) (1986)",
  "synonyms": [],
  "remark": "In order to be able to consider the input impedance as a pure resistance, the measurement signal frequency must be sufficiently low so that there are no significant phase differences between the voltages at the input terminals of the amplifier to be measured with or without the series resistor.",
  "remark_ml": {
    "en": "In order to be able to consider the input impedance as a pure resistance, the measurement signal frequency must be sufficiently low so that there are no significant phase differences between the voltages at the input terminals of the amplifier to be measured with or without the series resistor."
  },
  "status_level": "Standard",
  "publisher": "IEC",
  "published_in": "IEC 61360-4",
  "responsible_committee": "SC3D",
  "raw_properties": {
    "MDC_P001_6": "0112/2///61360_4#AAF163",
    "MDC_P002_1": "1",
    "MDC_P002_2": "5",
    "MDC_P004.en": "differential input resistance",
    "MDC_P005.en": "r_id",
    "MDC_P006.en": "minimum resistance between the inputs of a differential amplifier at reference conditions",
    "MDC_P009.en": "In order to be able to consider the input impedance as a pure resistance, the measurement signal frequency must be sufficiently low so that there are no significant phase differences between the voltages at the input terminals of the amplifier to be measured with or without the series resistor.",
    "MDC_P025_1": "r_id}",
    "MDC_P023": "Ω",
    "MDC_P022": "LEVEL(MIN) OF REAL_MEASURE_TYPE",
    "MDC_P024": "NR3..3.3ES2",
    "MDC_P006_1": "IEC 60748-3 (II.2.1.10) (1986)",
    "MDC_P020": "DEPENDENT_P_DET",
    "MDC_P040": "E33",
    "MDC_P021": "0112/2///61360_4#AAA001",
    "MDC_P041": "0112/2///62720#UAA017",
    "C016": "Standard",
    "C012": "IEC 61360-4",
    "C011": "IEC",
    "MDC_P003_0": "2015-08-17",
    "MDC_P003_1": "1996-08-01",
    "MDC_P003_2": "2011-08-31",
    "MDC_P003_3": "2015-08-17",
    "MDC_P012": "SC3D",
    "MDC_P028": "{0112/2///61360_4#AAE995}"
  },
  "version_history": [
    {
      "version": "001",
      "revision": "05",
      "status": "standard",
      "timestamp": "2015-08-17 15:40:37",
      "user": "BATCH 00000917",
      "unid": "9299774C44F6B386C1257EA4004B218F",
      "is_current": true
    },
    {
      "version": "001",
      "revision": "04",
      "status": "superseded",
      "timestamp": "2015-07-23 11:08:30",
      "user": "BATCH 00000907",
      "unid": "bcd837a6f3c4ffe0c1257e8b003237d8",
      "is_current": false
    },
    {
      "version": "001",
      "revision": "03",
      "status": "superseded",
      "timestamp": "2015-07-22 14:21:37",
      "user": "BATCH 00000904",
      "unid": "b3df1aba47618d55c1257e8a0043e5b2",
      "is_current": false
    },
    {
      "version": "001",
      "revision": "02",
      "status": "superseded",
      "timestamp": "2012-05-30 15:03:36",
      "user": "BATCH 00000788",
      "unid": "cee433f4ec500e35c1257a0e0047bdec",
      "is_current": false
    },
    {
      "version": "001",
      "revision": "01",
      "status": "superseded",
      "timestamp": "2012-05-30 14:53:56",
      "user": "BATCH 00000787",
      "unid": "f812203c68f3cccfc1257a0e0046db6c",
      "is_current": false
    }
  ],
  "dates": {
    "original_definition": "1996-08-01",
    "current_version": "2011-08-31",
    "current_revision": "2015-08-17"
  },
  "symbol_in_text": "r_id}",
  "value_format": "NR3..3.3ES2",
  "definition_class_irdi": "0112/2///61360_4#AAA001",
  "unit_irdi": "0112/2///62720#UAA017",
  "alternative_unit_irdis": [],
  "parsed_data_type": "LEVEL(MIN) OF REAL_MEASURE_TYPE",
  "data_element_type": "DEPENDENT_P_DET",
  "property_data_element_type": "DEPENDENT_P_DET",
  "condition_raw": "{0112/2///61360_4#AAE995}",
  "type": "property",
  "data_type": "LEVEL(MIN) OF REAL_MEASURE_TYPE",
  "is_current": true,
  "version_meta": {
    "version": "001",
    "revision": "05",
    "status": "standard",
    "timestamp": "2015-08-17 15:40:37",
    "user": "BATCH 00000917",
    "change_request_id": null,
    "unid": "9299774C44F6B386C1257EA4004B218F"
  }
}