{
  "irdi": "0112/2///61360_4#AAF998",
  "code": "AAF998",
  "version": "1",
  "revision": "4",
  "preferred_name": "expected marine growth",
  "preferred_name_ml": {
    "en": "expected marine growth",
    "de": "erwarteter Meeresbewuchs"
  },
  "definition": "description of the marine fauna and flora types expected to occur and populating submarine installations",
  "definition_ml": {
    "en": "description of the marine fauna and flora types expected to occur and populating submarine installations"
  },
  "source_document": "CIGRE 483 Guidelines for the Design and Construction of AC Offshore Substations for Wind Power Plants",
  "synonyms": [],
  "status_level": "Standard",
  "responsible_committee": "TC3, SC3D",
  "raw_properties": {
    "MDC_P001_6": "0112/2///61360_4#AAF998",
    "MDC_P002_1": "1",
    "MDC_P002_2": "4",
    "MDC_P004.en": "expected marine growth",
    "MDC_P006.en": "description of the marine fauna and flora types expected to occur and populating submarine installations",
    "MDC_P022": "STRING_TYPE",
    "MDC_P024": "M..70",
    "MDC_P006_1": "CIGRE 483 Guidelines for the Design and Construction of AC Offshore Substations for Wind Power Plants",
    "MDC_P020": "NON_DEPENDENT_P_DET",
    "MDC_P040": "X99",
    "MDC_P021": "0112/2///61360_4#AAA233",
    "C016": "Standard",
    "MDC_P003_0": "2015-08-17",
    "MDC_P003_2": "2013-07-04",
    "MDC_P003_3": "2015-08-17",
    "MDC_P012": "TC3, SC3D",
    "MDC_P004.de": "erwarteter Meeresbewuchs"
  },
  "version_history": [
    {
      "version": "001",
      "revision": "04",
      "status": "standard",
      "timestamp": "2015-08-17 15:40:41",
      "user": "BATCH 00000917",
      "unid": "A13DC524A9F1EEE5C1257EA4004B2324",
      "is_current": true
    },
    {
      "version": "001",
      "revision": "03",
      "status": "superseded",
      "timestamp": "2015-07-23 11:08:34",
      "user": "BATCH 00000907",
      "unid": "ad5945a5b793758bc1257e8b00323953",
      "is_current": false
    },
    {
      "version": "001",
      "revision": "02",
      "status": "superseded",
      "timestamp": "2015-07-22 14:21:41",
      "user": "BATCH 00000904",
      "unid": "72be1952dbd5bd65c1257e8a0043e747",
      "is_current": false
    },
    {
      "version": "001",
      "revision": "01",
      "status": "superseded",
      "timestamp": "2013-07-04 14:32:39",
      "user": "BATCH 00000825",
      "unid": "c32aa036c85a7ac7c1257b9e0044e899",
      "is_current": false
    }
  ],
  "dates": {
    "current_version": "2013-07-04",
    "current_revision": "2015-08-17"
  },
  "value_format": "M..70",
  "definition_class_irdi": "0112/2///61360_4#AAA233",
  "alternative_unit_irdis": [],
  "parsed_data_type": "STRING_TYPE",
  "data_element_type": "NON_DEPENDENT_P_DET",
  "property_data_element_type": "NON_DEPENDENT_P_DET",
  "parsed_value_format": "M..70",
  "type": "property",
  "data_type": "STRING_TYPE",
  "is_current": true,
  "version_meta": {
    "version": "001",
    "revision": "04",
    "status": "standard",
    "timestamp": "2015-08-17 15:40:41",
    "user": "BATCH 00000917",
    "change_request_id": null,
    "unid": "A13DC524A9F1EEE5C1257EA4004B2324"
  }
}