{
  "irdi": "0112/2///61987#ABC150",
  "code": "ABC150",
  "version": "1",
  "revision": "2",
  "preferred_name": "Calculated maximum electrical parameters for connected device",
  "preferred_name_ml": {
    "en": "Calculated maximum electrical parameters for connected device",
    "fr": "Paramètres électriques maximaux pour un appareil connecté",
    "de": "Berechnete maximale elektrische Werte für das angeschlossene Gerät"
  },
  "definition": "properties characterizing the electrical configuration of a device to be connected to the power source based on the electrical properties of the power source and the cable provided",
  "definition_ml": {
    "en": "properties characterizing the electrical configuration of a device to be connected to the power source based on the electrical properties of the power source and the cable provided",
    "fr": "propriétés caractérisant la configuration électriques d’un appareil à connecter à la source d’alimentation sur la base des propriétés électriques de la source d’alimentation et du câble fourni",
    "de": "Merkmale, die die elektrische Konfiguration eines an eine Stromquelle anzuschließenden Geräts anhand der elektrischen Merkmale der bereitgestellten Stromquelle und des Kabels kennzeichnen"
  },
  "synonyms": [],
  "status_level": "Standard",
  "responsible_committee": "SC65E – IEC 61987",
  "change_request_id": "C00004",
  "raw_properties": {
    "MDC_P001_5": "0112/2///61987#ABC150",
    "MDC_P002_1": "1",
    "MDC_P002_2": "2",
    "MDC_P004.en": "Calculated maximum electrical parameters for connected device",
    "MDC_P006.en": "properties characterizing the electrical configuration of a device to be connected to the power source based on the electrical properties of the power source and the cable provided",
    "MDC_P011": "ITEM_CLASS",
    "C016": "Standard",
    "MDC_P003_0": "2018-03-28",
    "MDC_P003_1": "2013-08-27",
    "MDC_P003_2": "2013-08-27",
    "MDC_P003_3": "2014-06-18",
    "MDC_P012": "SC65E – IEC 61987",
    "MDC_P010": "0112/2///61987#ABV501",
    "MDC_P014": "{0112/2///61987#ABB352,0112/2///61987#ABB353,0112/2///61987#ABB354}",
    "MDC_P004.fr": "Paramètres électriques maximaux pour un appareil connecté",
    "MDC_P006.fr": "propriétés caractérisant la configuration électriques d’un appareil à connecter à la source d’alimentation sur la base des propriétés électriques de la source d’alimentation et du câble fourni",
    "C019.fr": "Mr. W. Hartmann",
    "C017.fr": "0",
    "C018.fr": "2013-11-28",
    "MDC_P004.de": "Berechnete maximale elektrische Werte für das angeschlossene Gerät",
    "MDC_P006.de": "Merkmale, die die elektrische Konfiguration eines an eine Stromquelle anzuschließenden Geräts anhand der elektrischen Merkmale der bereitgestellten Stromquelle und des Kabels kennzeichnen",
    "C019.de": "Mr. W. Hartmann",
    "C017.de": "0",
    "C018.de": "2014-12-12",
    "C002": "C00004"
  },
  "version_history": [
    {
      "version": "001",
      "revision": "02",
      "status": "standard",
      "timestamp": "2018-03-28 07:25:50",
      "user": "BATCH 00000762",
      "unid": "E21BFDC7589662EDC125825E001DD4F1",
      "is_current": true
    },
    {
      "version": "001",
      "revision": "01",
      "status": "superseded",
      "timestamp": "2014-04-08 17:24:07",
      "user": "BATCH 00000699",
      "unid": "bb0c86311085ee57c1257cb400549b5c",
      "is_current": false
    }
  ],
  "dates": {
    "original_definition": "2013-08-27",
    "current_version": "2013-08-27",
    "current_revision": "2014-06-18"
  },
  "is_case_of": [],
  "applicable_properties": [
    "0112/2///61987#ABB352",
    "0112/2///61987#ABB353",
    "0112/2///61987#ABB354"
  ],
  "imported_properties": [],
  "sub_class_selection": [],
  "applicable_documents": [],
  "imported_documents": [],
  "class_type": "ITEM_CLASS",
  "superclass": "0112/2///61987#ABV501",
  "superclass_type_property": "0112/2///61987#ABV501",
  "type": "class",
  "is_current": true,
  "version_meta": {
    "version": "001",
    "revision": "02",
    "status": "standard",
    "timestamp": "2018-03-28 07:25:50",
    "user": "BATCH 00000762",
    "change_request_id": null,
    "unid": "E21BFDC7589662EDC125825E001DD4F1"
  }
}