{
  "irdi": "0112/2///62683#ACE721",
  "code": "ACE721",
  "version": "2",
  "revision": "1",
  "preferred_name": "rated operational voltage for IT systems",
  "preferred_name_ml": {
    "en": "rated operational voltage for IT systems",
    "fr": "tension assignée d'emploi pour réseaux IT",
    "de": "Bemessungsbetriebs-spannung für IT-Systeme",
    "zh": "IT系统额定工作电压"
  },
  "definition": "maximum value of the rated operational voltage for which the device is suitable for use on IT systems",
  "definition_ml": {
    "en": "maximum value of the rated operational voltage for which the device is suitable for use on IT systems",
    "fr": "valeur maximum de la tension assignée d'emploi pour laquelle l'appareil est apte à être utilisé dans des réseaux IT",
    "de": "maximaler Wert der Bemessungsbetriebsspannung für den das Gerät für den Gebrauch in IT-Systemen geeignet ist.",
    "zh": "使电器适用于IT系统的额定工作电压最大值"
  },
  "synonyms": [],
  "status_level": "Standard",
  "publisher": "IEC",
  "responsible_committee": "IEC/TC 121",
  "change_request_id": "C00159",
  "raw_properties": {
    "MDC_P001_6": "0112/2///62683#ACE721",
    "MDC_P002_1": "2",
    "MDC_P002_2": "1",
    "MDC_P004.en": "rated operational voltage for IT systems",
    "MDC_P006.en": "maximum value of the rated operational voltage for which the device is suitable for use on IT systems",
    "MDC_P022": "ENUM_STRING_TYPE(0112/2///62683#ACI101)",
    "MDC_P024": "X..5",
    "MDC_P020": "NON_DEPENDENT_P_DET",
    "MDC_P021": "0112/2///62683#ACC040",
    "C016": "Standard",
    "C011": "IEC",
    "MDC_P003_0": "2024-05-07",
    "MDC_P003_1": "2013-01-30",
    "MDC_P003_2": "2024-05-06",
    "MDC_P003_3": "2024-05-06",
    "MDC_P012": "IEC/TC 121",
    "MDC_P004.fr": "tension assignée d'emploi pour réseaux IT",
    "MDC_P006.fr": "valeur maximum de la tension assignée d'emploi pour laquelle l'appareil est apte à être utilisé dans des réseaux IT",
    "C019.fr": "IEC 121A/WG 17",
    "C017.fr": "1",
    "C018.fr": "2012-09-27",
    "MDC_P004.de": "Bemessungsbetriebs-spannung für IT-Systeme",
    "MDC_P006.de": "maximaler Wert der Bemessungsbetriebsspannung für den das Gerät für den Gebrauch in IT-Systemen geeignet ist.",
    "C019.de": "DKE, Jürgen Schütz",
    "C017.de": "1",
    "C018.de": "2017-06-15",
    "MDC_P004.zh": "IT系统额定工作电压",
    "MDC_P006.zh": "使电器适用于IT系统的额定工作电压最大值",
    "C019.zh": "SAC, Li Hui",
    "C017.zh": "1",
    "C018.zh": "2017-09-26",
    "C002": "C00159"
  },
  "version_history": [
    {
      "version": "002",
      "revision": "01",
      "status": "standard",
      "timestamp": "2024-05-07 21:51:19",
      "user": "BATCH 00000806",
      "unid": "EDF67B920CF1A3BEC1258B16006D119A",
      "is_current": true
    },
    {
      "version": "001",
      "revision": "01",
      "status": "superseded",
      "timestamp": "2020-01-11 20:58:49",
      "user": "BATCH 00000741",
      "unid": "c33c17c71b1a252bc12584ec006dc16f",
      "is_current": false
    },
    {
      "version": "001",
      "revision": "01",
      "status": "superseded",
      "timestamp": "2016-09-16 14:38:29",
      "user": "BATCH 00000704",
      "unid": "0386762d89232411c1258030004570f6",
      "is_current": false
    }
  ],
  "dates": {
    "original_definition": "2013-01-30",
    "current_version": "2024-05-06",
    "current_revision": "2024-05-06"
  },
  "value_format": "X..5",
  "definition_class_irdi": "0112/2///62683#ACC040",
  "alternative_unit_irdis": [],
  "parsed_data_type": "ENUM_STRING_TYPE(0112/2///62683#ACI101)",
  "data_element_type": "NON_DEPENDENT_P_DET",
  "property_data_element_type": "NON_DEPENDENT_P_DET",
  "type": "property",
  "data_type": "ENUM_STRING_TYPE(0112/2///62683#ACI101)",
  "value_list": "0112/2///62683#ACI101",
  "is_current": true,
  "version_meta": {
    "version": "002",
    "revision": "01",
    "status": "standard",
    "timestamp": "2024-05-07 21:51:19",
    "user": "BATCH 00000806",
    "change_request_id": null,
    "unid": "EDF67B920CF1A3BEC1258B16006D119A"
  }
}