{
  "irdi": "0112/2///61987#ABA973",
  "code": "ABA973",
  "version": "6",
  "revision": "1",
  "preferred_name": "minimum supply frequency",
  "preferred_name_ml": {
    "en": "minimum supply frequency",
    "fr": "fréquence d'alimentation minimale",
    "de": "minimale Versorgungsfrequenz"
  },
  "definition": "lowest frequency of a power supply with which the device can be operated",
  "definition_ml": {
    "en": "lowest frequency of a power supply with which the device can be operated",
    "fr": "fréquence de l'alimentation de courant auxiliaire la plus faible avec laquelle l’appareil peut fonctionner",
    "de": "niedrigste Frequenz der Energieversorgung, mit der das Gerät betrieben werden kann"
  },
  "synonyms": [],
  "status_level": "Standard",
  "publisher": "IEC",
  "published_in": "IEC 61987",
  "responsible_committee": "IEC/SC 65E",
  "change_request_id": "C00112",
  "raw_properties": {
    "MDC_P001_6": "0112/2///61987#ABA973",
    "MDC_P002_1": "6",
    "MDC_P002_2": "1",
    "MDC_P004.en": "minimum supply frequency",
    "MDC_P006.en": "lowest frequency of a power supply with which the device can be operated",
    "MDC_P023": "Hz",
    "MDC_P022": "REAL_MEASURE_TYPE",
    "MDC_P020": "NON_DEPENDENT_P_DET",
    "MDC_P021": "0112/2///61987#ABA000",
    "MDC_P041": "0112/2///62720#UAA170",
    "C0104": "0112/2///61987#ABT561",
    "C016": "Standard",
    "C012": "IEC 61987",
    "C011": "IEC",
    "MDC_P003_0": "2022-12-09",
    "MDC_P003_1": "2017-12-07",
    "MDC_P003_2": "2022-12-09",
    "MDC_P003_3": "2022-12-09",
    "MDC_P012": "IEC/SC 65E",
    "MDC_P004.fr": "fréquence d'alimentation minimale",
    "MDC_P006.fr": "fréquence de l'alimentation de courant auxiliaire la plus faible avec laquelle l’appareil peut fonctionner",
    "C019.fr": "Mr. W. Hartmann",
    "C017.fr": "0",
    "C018.fr": "2013-04-21",
    "MDC_P004.de": "minimale Versorgungsfrequenz",
    "MDC_P006.de": "niedrigste Frequenz der Energieversorgung, mit der das Gerät betrieben werden kann",
    "C019.de": "Mr. W. Hartmann",
    "C017.de": "1",
    "C018.de": "2021-08-12",
    "C002": "C00112"
  },
  "version_history": [
    {
      "version": "006",
      "revision": "01",
      "status": "standard",
      "timestamp": "2022-12-09 09:47:22",
      "user": "BATCH 00000803",
      "unid": "21EB310E84611391C12589130030482C",
      "is_current": true
    },
    {
      "version": "005",
      "revision": "01",
      "status": "superseded",
      "timestamp": "2018-03-28 07:26:38",
      "user": "BATCH 00000762",
      "unid": "f2286364719f4728c125825e001de7c8",
      "is_current": false
    },
    {
      "version": "004",
      "revision": "01",
      "status": "superseded",
      "timestamp": "2018-03-20 12:23:33",
      "user": "BATCH 00000755",
      "unid": "b20e00ba47f7d512c1258256003e94d2",
      "is_current": false
    },
    {
      "version": "003",
      "revision": "02",
      "status": "superseded",
      "timestamp": "2017-03-01 14:51:20",
      "user": "BATCH 00000732",
      "unid": "1ff20df5613f8cbbc12580d6004c1c77",
      "is_current": false
    },
    {
      "version": "003",
      "revision": "01",
      "status": "superseded",
      "timestamp": "2016-03-23 15:01:05",
      "user": "BATCH 00000715",
      "unid": "124329cda30c6ca6c1257f7f004d010f",
      "is_current": false
    },
    {
      "version": "002",
      "revision": "01",
      "status": "superseded",
      "timestamp": "2016-05-02 12:36:07",
      "user": "BATCH 00000716",
      "unid": "356f85202b521534c1257fa7003a3d18",
      "is_current": false
    },
    {
      "version": "001",
      "revision": "02",
      "status": "superseded",
      "timestamp": "2014-06-18 13:41:32",
      "user": "BATCH 00000702",
      "unid": "4480d9efbf530c0ec1257cfb00403a51",
      "is_current": false
    },
    {
      "version": "001",
      "revision": "01",
      "status": "superseded",
      "timestamp": "2014-04-08 17:25:31",
      "user": "BATCH 00000699",
      "unid": "440c948f24cacd99c1257cb40054bc0e",
      "is_current": false
    }
  ],
  "dates": {
    "original_definition": "2017-12-07",
    "current_version": "2022-12-09",
    "current_revision": "2022-12-09"
  },
  "definition_class_irdi": "0112/2///61987#ABA000",
  "unit_irdi": "0112/2///62720#UAA170",
  "alternative_unit_irdis": [],
  "parsed_data_type": "REAL_MEASURE_TYPE",
  "data_element_type": "NON_DEPENDENT_P_DET",
  "property_data_element_type": "NON_DEPENDENT_P_DET",
  "type": "property",
  "data_type": "REAL_MEASURE_TYPE",
  "is_current": true,
  "version_meta": {
    "version": "006",
    "revision": "01",
    "status": "standard",
    "timestamp": "2022-12-09 09:47:22",
    "user": "BATCH 00000803",
    "change_request_id": null,
    "unid": "21EB310E84611391C12589130030482C"
  }
}