{
  "irdi": "0112/2///61987#ABA243",
  "code": "ABA243",
  "version": "7",
  "revision": "1",
  "preferred_name": "type of overfill prevention approval",
  "preferred_name_ml": {
    "en": "type of overfill prevention approval",
    "fr": "type d'agrément de prévention des débordements",
    "de": "Art der Überfüllsicherungszulassung"
  },
  "definition": "classification of an overspill protection approval according to an issuing regulatory authority",
  "definition_ml": {
    "en": "classification of an overspill protection approval according to an issuing regulatory authority",
    "fr": "classification d'un agrément de protection contre les débordements selon une autorité réglementaire émettrice",
    "de": "Charakterisierung einer Überfüllsicherungszulassung bezüglich der herausgebenden Regulierungsstelle"
  },
  "synonyms": [],
  "status_level": "Standard",
  "publisher": "IEC",
  "published_in": "IEC 61987",
  "responsible_committee": "IEC/SC 65E",
  "change_request_id": "C00185",
  "raw_properties": {
    "MDC_P001_6": "0112/2///61987#ABA243",
    "MDC_P002_1": "7",
    "MDC_P002_2": "1",
    "MDC_P004.en": "type of overfill prevention approval",
    "MDC_P006.en": "classification of an overspill protection approval according to an issuing regulatory authority",
    "MDC_P022": "ENUM_STRING_TYPE(0112/2///61987#ABL693)",
    "MDC_P020": "DEPENDENT_P_DET",
    "MDC_P021": "0112/2///61987#ABA000",
    "C016": "Standard",
    "C012": "IEC 61987",
    "C011": "IEC",
    "MDC_P003_0": "2025-08-04",
    "MDC_P003_1": "2017-12-07",
    "MDC_P003_2": "2025-08-04",
    "MDC_P003_3": "2025-08-04",
    "MDC_P012": "IEC/SC 65E",
    "MDC_P028": "{0112/2///61987#ABI406}",
    "MDC_P004.fr": "type d'agrément de prévention des débordements",
    "MDC_P006.fr": "classification d'un agrément de protection contre les débordements selon une autorité réglementaire émettrice",
    "C019.fr": "Mr. W. Hartmann",
    "C017.fr": "0",
    "C018.fr": "2013-04-21",
    "MDC_P004.de": "Art der Überfüllsicherungszulassung",
    "MDC_P006.de": "Charakterisierung einer Überfüllsicherungszulassung bezüglich der herausgebenden Regulierungsstelle",
    "C019.de": "Mr. W. Hartmann",
    "C017.de": "0",
    "C018.de": "2013-10-16",
    "C002": "C00185"
  },
  "version_history": [
    {
      "version": "007",
      "revision": "01",
      "status": "standard",
      "timestamp": "2025-08-04 15:30:46",
      "user": "BATCH 00000849",
      "unid": "80E471361FBE72E2C1258CDC004A3A63",
      "is_current": true
    },
    {
      "version": "006",
      "revision": "01",
      "status": "superseded",
      "timestamp": "2020-02-24 11:58:26",
      "user": "BATCH 00000774",
      "unid": "7e2a600f610c82ccc1258518003c4831",
      "is_current": false
    },
    {
      "version": "005",
      "revision": "01",
      "status": "superseded",
      "timestamp": "2018-03-28 07:26:34",
      "user": "BATCH 00000762",
      "unid": "19c5d80356c896b4c125825e001de5f4",
      "is_current": false
    },
    {
      "version": "004",
      "revision": "01",
      "status": "superseded",
      "timestamp": "2017-03-01 14:51:15",
      "user": "BATCH 00000732",
      "unid": "25f78cb246436cf8c12580d6004c1ac4",
      "is_current": false
    },
    {
      "version": "003",
      "revision": "01",
      "status": "superseded",
      "timestamp": "2016-03-22 09:54:35",
      "user": "BATCH 00000714",
      "unid": "6935693b7994a32bc1257f7e0030f1a7",
      "is_current": false
    },
    {
      "version": "002",
      "revision": "01",
      "status": "superseded",
      "timestamp": "2016-05-02 12:36:06",
      "user": "BATCH 00000716",
      "unid": "09576203409b9e75c1257fa7003a3cde",
      "is_current": false
    },
    {
      "version": "001",
      "revision": "02",
      "status": "superseded",
      "timestamp": "2014-06-18 13:41:27",
      "user": "BATCH 00000702",
      "unid": "4826293e86ff568bc1257cfb0040389e",
      "is_current": false
    },
    {
      "version": "001",
      "revision": "01",
      "status": "superseded",
      "timestamp": "2014-04-08 17:25:27",
      "user": "BATCH 00000699",
      "unid": "5662c5ba26b48bd7c1257cb40054ba5b",
      "is_current": false
    }
  ],
  "dates": {
    "original_definition": "2017-12-07",
    "current_version": "2025-08-04",
    "current_revision": "2025-08-04"
  },
  "definition_class_irdi": "0112/2///61987#ABA000",
  "alternative_unit_irdis": [],
  "parsed_data_type": "ENUM_STRING_TYPE(0112/2///61987#ABL693)",
  "data_element_type": "DEPENDENT_P_DET",
  "property_data_element_type": "DEPENDENT_P_DET",
  "condition_raw": "{0112/2///61987#ABI406}",
  "type": "property",
  "data_type": "ENUM_STRING_TYPE(0112/2///61987#ABL693)",
  "value_list": "0112/2///61987#ABL693",
  "is_current": true,
  "version_meta": {
    "version": "007",
    "revision": "01",
    "status": "standard",
    "timestamp": "2025-08-04 15:30:46",
    "user": "BATCH 00000849",
    "change_request_id": null,
    "unid": "80E471361FBE72E2C1258CDC004A3A63"
  }
}