{
  "irdi": "0112/2///61987#ABC278",
  "code": "ABC278",
  "version": "1",
  "revision": "3",
  "preferred_name": "Influence of external quantities expressed for dynamic viscosity",
  "preferred_name_ml": {
    "en": "Influence of external quantities expressed for dynamic viscosity",
    "fr": "Influence de grandeurs externes exprimée en pourcentage pour viscosité dynamique",
    "de": "Einfluss der externen Größen für dynamische Viskositätsmessung"
  },
  "definition": "properties characterizing the influence of external quantities for dynamic viscosity measurement devices that are not the subject of the measurement but whose change affects the relationship between the indication and the result of the measurement",
  "definition_ml": {
    "en": "properties characterizing the influence of external quantities for dynamic viscosity measurement devices that are not the subject of the measurement but whose change affects the relationship between the indication and the result of the measurement",
    "fr": "propriétés caractérisant l’influence de grandeurs externes pour des appareils de mesure de viscosité dynamique qui ne sont pas l'objet de la mesure mais dont le changement affecte la relation entre l’indication et le résultat de la mesure",
    "de": "Merkmale, die den Einfluss von externen Größen auf die dynamische Viskositätsmesseinrichtung kennzeichnen, die nicht Gegenstand der Messung sind, aber deren Änderung die Beziehung zwischen Messergebnis und Anzeige beeinflusst"
  },
  "synonyms": [],
  "status_level": "Standard",
  "publisher": "IEC",
  "published_in": "IEC 61987",
  "responsible_committee": "IEC/SC 65E",
  "change_request_id": "C00200",
  "raw_properties": {
    "MDC_P001_5": "0112/2///61987#ABC278",
    "MDC_P002_1": "1",
    "MDC_P002_2": "3",
    "MDC_P004.en": "Influence of external quantities expressed for dynamic viscosity",
    "MDC_P006.en": "properties characterizing the influence of external quantities for dynamic viscosity measurement devices that are not the subject of the measurement but whose change affects the relationship between the indication and the result of the measurement",
    "MDC_P011": "ITEM_CLASS",
    "MDC_P019": "false",
    "C016": "Standard",
    "C012": "IEC 61987",
    "C011": "IEC",
    "MDC_P003_0": "2026-05-04",
    "MDC_P003_1": "2017-12-07",
    "MDC_P003_2": "2017-12-07",
    "MDC_P003_3": "2026-05-04",
    "MDC_P012": "IEC/SC 65E",
    "MDC_P010": "0112/2///61987#ABV501",
    "MDC_P014": "{0112/2///61987#ABB831,0112/2///61987#ABB832,0112/2///61987#ABB833,0112/2///61987#ABB834,0112/2///61987#ABB835,0112/2///61987#ABB836}",
    "MDC_P004.fr": "Influence de grandeurs externes exprimée en pourcentage pour viscosité dynamique",
    "MDC_P006.fr": "propriétés caractérisant l’influence de grandeurs externes pour des appareils de mesure de viscosité dynamique qui ne sont pas l'objet de la mesure mais dont le changement affecte la relation entre l’indication et le résultat de la mesure",
    "C019.fr": "Mr. W. Hartmann",
    "C017.fr": "1",
    "C018.fr": "2026-03-16",
    "MDC_P004.de": "Einfluss der externen Größen für dynamische Viskositätsmessung",
    "MDC_P006.de": "Merkmale, die den Einfluss von externen Größen auf die dynamische Viskositätsmesseinrichtung kennzeichnen, die nicht Gegenstand der Messung sind, aber deren Änderung die Beziehung zwischen Messergebnis und Anzeige beeinflusst",
    "C019.de": "Mr. W. Hartmann",
    "C017.de": "0",
    "C018.de": "2014-12-12",
    "C002": "C00200"
  },
  "version_history": [
    {
      "version": "001",
      "revision": "03",
      "status": "standard",
      "timestamp": "2026-05-04 14:34:43",
      "user": "BATCH 00000863",
      "unid": "03E6DEB69B38CF74C1258DED004518F8",
      "is_current": true
    },
    {
      "version": "001",
      "revision": "02",
      "status": "superseded",
      "timestamp": "2018-03-28 07:25:52",
      "user": "BATCH 00000762",
      "unid": "b119cdd8528bb953c125825e001dd5c1",
      "is_current": false
    },
    {
      "version": "001",
      "revision": "01",
      "status": "superseded",
      "timestamp": "2014-04-08 17:24:09",
      "user": "BATCH 00000699",
      "unid": "bcd389bb237079b9c1257cb400549bd9",
      "is_current": false
    }
  ],
  "dates": {
    "original_definition": "2017-12-07",
    "current_version": "2017-12-07",
    "current_revision": "2026-05-04"
  },
  "is_case_of": [],
  "applicable_properties": [
    "0112/2///61987#ABB831",
    "0112/2///61987#ABB832",
    "0112/2///61987#ABB833",
    "0112/2///61987#ABB834",
    "0112/2///61987#ABB835",
    "0112/2///61987#ABB836"
  ],
  "imported_properties": [],
  "sub_class_selection": [],
  "applicable_documents": [],
  "imported_documents": [],
  "class_type": "ITEM_CLASS",
  "superclass": "0112/2///61987#ABV501",
  "superclass_type_property": "0112/2///61987#ABV501",
  "type": "class",
  "is_current": true,
  "version_meta": {
    "version": "001",
    "revision": "03",
    "status": "standard",
    "timestamp": "2026-05-04 14:34:43",
    "user": "BATCH 00000863",
    "change_request_id": null,
    "unid": "03E6DEB69B38CF74C1258DED004518F8"
  }
}