{
  "irdi": "0112/2///61987#ABD868",
  "code": "ABD868",
  "version": "2",
  "revision": "1",
  "preferred_name": "Explosion protection design approval [2]",
  "preferred_name_ml": {
    "en": "Explosion protection design approval [2]",
    "fr": "Agréments de conception de protection contre les explosions [2]",
    "de": "Explosionsschutzausführung [2]"
  },
  "definition": "properties characterizing an explosion protection design approval",
  "definition_ml": {
    "en": "properties characterizing an explosion protection design approval",
    "fr": "propriétés caractérisant un agrément de conception de protection contre les explosions",
    "de": "Merkmale, die eine Zulassung für eine Explosionsschutzausführung kennzeichnen"
  },
  "synonyms": [],
  "status_level": "Standard",
  "responsible_committee": "SC65E – IEC 61987",
  "change_request_id": "C00004",
  "raw_properties": {
    "MDC_P001_5": "0112/2///61987#ABD868",
    "MDC_P002_1": "2",
    "MDC_P002_2": "1",
    "MDC_P004.en": "Explosion protection design approval [2]",
    "MDC_P006.en": "properties characterizing an explosion protection design approval",
    "MDC_P011": "ITEM_CLASS",
    "C016": "Standard",
    "MDC_P003_0": "2018-03-28",
    "MDC_P003_1": "2013-09-02",
    "MDC_P003_2": "2018-03-20",
    "MDC_P003_3": "2018-03-20",
    "MDC_P012": "SC65E – IEC 61987",
    "MDC_P010": "0112/2///61987#ABV501",
    "MDC_P014": "{0112/2///61987#ABB991,0112/2///61987#ABB385,0112/2///61987#ABB146,0112/2///61987#ABA462,0112/2///61987#ABA960,0112/2///61987#ABB013,0112/2///61987#ABA961,0112/2///61987#ABA463,0112/2///61987#ABA595,0112/2///61987#ABA464,0112/2///61987#ABA465,0112/2///61987#ABC820,0112/2///61987#ABA589,0112/2///61987#ABA593,0112/2///61987#ABB159,0112/2///61987#ABA468}",
    "MDC_P004.fr": "Agréments de conception de protection contre les explosions [2]",
    "MDC_P006.fr": "propriétés caractérisant un agrément de conception de protection contre les explosions",
    "C019.fr": "Mr. W. Hartmann",
    "C017.fr": "0",
    "C018.fr": "2013-11-24",
    "MDC_P004.de": "Explosionsschutzausführung [2]",
    "MDC_P006.de": "Merkmale, die eine Zulassung für eine Explosionsschutzausführung kennzeichnen",
    "C019.de": "Mr. W. Hartmann",
    "C017.de": "0",
    "C018.de": "2014-12-12",
    "C002": "C00004"
  },
  "version_history": [
    {
      "version": "002",
      "revision": "01",
      "status": "standard",
      "timestamp": "2018-03-28 07:26:00",
      "user": "BATCH 00000762",
      "unid": "D8ACA2EB23AA449EC125825E001DD8CA",
      "is_current": true
    },
    {
      "version": "001",
      "revision": "02",
      "status": "superseded",
      "timestamp": "2017-03-01 14:50:05",
      "user": "BATCH 00000732",
      "unid": "be23065d3ae2d400c12580d6004bff66",
      "is_current": false
    },
    {
      "version": "001",
      "revision": "01",
      "status": "superseded",
      "timestamp": "2014-04-08 17:24:13",
      "user": "BATCH 00000699",
      "unid": "c2b4a142f55825e4c1257cb400549da8",
      "is_current": false
    }
  ],
  "dates": {
    "original_definition": "2013-09-02",
    "current_version": "2018-03-20",
    "current_revision": "2018-03-20"
  },
  "is_case_of": [],
  "applicable_properties": [
    "0112/2///61987#ABB991",
    "0112/2///61987#ABB385",
    "0112/2///61987#ABB146",
    "0112/2///61987#ABA462",
    "0112/2///61987#ABA960",
    "0112/2///61987#ABB013",
    "0112/2///61987#ABA961",
    "0112/2///61987#ABA463",
    "0112/2///61987#ABA595",
    "0112/2///61987#ABA464",
    "0112/2///61987#ABA465",
    "0112/2///61987#ABC820",
    "0112/2///61987#ABA589",
    "0112/2///61987#ABA593",
    "0112/2///61987#ABB159",
    "0112/2///61987#ABA468"
  ],
  "imported_properties": [],
  "sub_class_selection": [],
  "applicable_documents": [],
  "imported_documents": [],
  "class_type": "ITEM_CLASS",
  "superclass": "0112/2///61987#ABV501",
  "superclass_type_property": "0112/2///61987#ABV501",
  "type": "class",
  "is_current": true,
  "version_meta": {
    "version": "002",
    "revision": "01",
    "status": "standard",
    "timestamp": "2018-03-28 07:26:00",
    "user": "BATCH 00000762",
    "change_request_id": null,
    "unid": "D8ACA2EB23AA449EC125825E001DD8CA"
  }
}